flake8_multiline_equals/__init__.py
flake8_multiline_equals/checker.py
flake8_multiline_equals-1.2.0.dist-info/licenses/LICENSE
flake8_multiline_equals-1.2.0.dist-info/METADATA
flake8_multiline_equals-1.2.0.dist-info/WHEEL
flake8_multiline_equals-1.2.0.dist-info/entry_points.txt
flake8_multiline_equals-1.2.0.dist-info/top_level.txt
flake8_multiline_equals-1.2.0.dist-info/RECORD
