Metadata-Version: 2.4
Name: flake8-multiline-equals
Version: 1.2.0
Summary: Highly opinionated: Spaces around `=` in multiline function calls
Author-email: Ashwin Panchapakesan <ashwin.panchapakesan@gmail.com>
License-Expression: MIT
Project-URL: Homepage, https://github.com/inspectorG4dget/flake8-multiline-equals
Project-URL: Issues, https://github.com/inspectorG4dget/flake8-multiline-equals/issues
Classifier: Programming Language :: Python :: 3
Classifier: Operating System :: OS Independent
Requires-Python: >=3.7
License-File: LICENSE
Requires-Dist: flake8
Dynamic: license-file
